process_metrics/__init__.py
process_metrics/__main__.py
process_metrics/metric_threshold.py
process_metrics/qc_validation_result.py
process_metrics/qc_validator.py
process_metrics/report_generator.py
process_metrics/threshold_file_parser.py
process_metrics/metrics/__init__.py
process_metrics/metrics/available_metrics.py
process_metrics/metrics/freemix.py
process_metrics/metrics/mean_coverage.py
process_metrics/metrics/mean_target_coverage.py
process_metrics/metrics/median_absolute_deviation.py
process_metrics/metrics/median_insert_size.py
process_metrics/metrics/metric.py
process_metrics/metrics/percent_10x.py
process_metrics/metrics/percent_20x.py
process_metrics/metrics/percent_30x.py
process_metrics/metrics/percent_chimeras.py
process_metrics/metrics/percent_duplication.py
process_metrics/metrics/percent_target_10x.py
process_metrics/metrics/percent_target_20x.py
process_metrics/metrics/percent_target_30x.py
process_metrics/metrics/q20_bases.py
process_metrics/metrics/read1_mismatch_rate.py
process_metrics/metrics/read2_mismatch_rate.py
process_metrics/metrics/tsv_metric.py
qc_metric_aggregator-0.1.5.dist-info/LICENSE
qc_metric_aggregator-0.1.5.dist-info/METADATA
qc_metric_aggregator-0.1.5.dist-info/WHEEL
qc_metric_aggregator-0.1.5.dist-info/entry_points.txt
qc_metric_aggregator-0.1.5.dist-info/top_level.txt
qc_metric_aggregator-0.1.5.dist-info/RECORD
