Metadata-Version: 2.1
Name: qc-metric-aggregator
Version: 0.1.5
Summary: Given the output directory of a QC pipeline and a threshold config file, parse out the desired metrics and evalute them against the thresholds.
Home-page: https://github.com/genome/qc-metric-aggregator
Author: Adam Coffman
Author-email: acoffman@wustl.edu
License: MIT
Platform: UNKNOWN
Classifier: License :: OSI Approved :: MIT License
Classifier: Programming Language :: Python :: 3
Classifier: Programming Language :: Python :: 3.7
Requires-Dist: pyyaml
